chatsh/__init__.py
chatsh/chat.py
chatsh/chat_vendors.py
chatsh/chatsh.py
chatsh/conversation.py
chatsh/interaction_log.py
chatsh/system.prompt
chatsh-0.3.2.dist-info/LICENSE
chatsh-0.3.2.dist-info/METADATA
chatsh-0.3.2.dist-info/WHEEL
chatsh-0.3.2.dist-info/entry_points.txt
chatsh-0.3.2.dist-info/RECORD
