Metadata-Version: 2.1
Name: chatsh
Version: 0.3.2
Summary: Syntax-highlighted Claude-controlled bash.
License: MIT
Author: Xida Ren
Author-email: cedar.ren@gmail.com
Requires-Python: >=3.8.1,<4.0
Classifier: Development Status :: 3 - Alpha
Classifier: License :: OSI Approved :: MIT License
Classifier: Programming Language :: Python :: 3
Classifier: Programming Language :: Python :: 3.9
Classifier: Programming Language :: Python :: 3.10
Classifier: Programming Language :: Python :: 3.11
Classifier: Programming Language :: Python :: 3.12
Classifier: Programming Language :: Python :: 3.13
Classifier: Topic :: Software Development :: Libraries :: Python Modules
Classifier: Topic :: Utilities
Requires-Dist: aiofiles (==24.1.0)
Requires-Dist: anthropic (>0.34.1)
Requires-Dist: dataclasses-json (>=0.5.7,<0.6.0)
Requires-Dist: prompt-toolkit (>=3.0.48,<4.0.0)
Requires-Dist: protobuf (==5.28.0)
Requires-Dist: rich (>=13.8.1,<14.0.0)
Requires-Dist: textual (>=0.83.0,<0.84.0)
Project-URL: Homepage, https://github.com/renxida/chatsh
